lumberman/__init__.py
lumberman/__main__.py
lumberman/git.py
lumberman/queue_manipulator.py
lumberman/cli/__init__.py
lumberman/cli/config.py
lumberman/cli/interface_elements.py
lumberman/cli/location.py
lumberman/cli/manipulation.py
lumberman/cli/markdown.py
lumberman/cli/navigation.py
lumberman/cli/subprocess_utils.py
lumberman/issues/__init__.py
lumberman/issues/controller.py
lumberman/issues/provider.py
lumberman/issues/selecter.py
lumberman/issues/stringifyer.py
lumberman/issues/test_issue_service.py
lumberman/issues/test_model.py
lumberman/issues/test_stringifyer.py
lumberman/issues/test_title_parser.py
lumberman/issues/title_parser.py
lumberman/stack/__init__.py
lumberman/stack/manipulator.py
lumberman/stack/navigator.py
lumberman-0.53.0.dist-info/LICENSE
lumberman-0.53.0.dist-info/METADATA
lumberman-0.53.0.dist-info/WHEEL
lumberman-0.53.0.dist-info/entry_points.txt
lumberman-0.53.0.dist-info/top_level.txt
lumberman-0.53.0.dist-info/RECORD
