Metadata-Version: 2.1
Name: lumberman
Version: 0.53.0
Summary: lumberman
Author-email: Martin Bernstorff <martinbernstorff@gmail.com>
License: MIT License
Project-URL: homepage, https://github.com/MartinBernstorff/lumberman
Project-URL: repository, https://github.com/MartinBernstorff/lumberman
Project-URL: documentation, https://MartinBernstorff.github.io/lumberman/
Classifier: Programming Language :: Python :: 3.10
Classifier: Programming Language :: Python :: 3.11
Classifier: Programming Language :: Python :: 3.12
Requires-Python: >=3.10
License-File: LICENSE
Requires-Dist: typer ==0.12.3
Requires-Dist: rich ==13.7.1
Requires-Dist: iterfzf >=1.1.0.44.0
